datapanels/__init__.py
datapanels/app.py
datapanels/gameoflife.py
datapanels/stockpanel.py
datapanels/util.py
datapanels/weather.py
datapanels/images/01d.png
datapanels/images/01n.png
datapanels/images/02d.png
datapanels/images/02n.png
datapanels/images/03d.png
datapanels/images/03n.png
datapanels/images/04d.png
datapanels/images/04n.png
datapanels/images/09d.png
datapanels/images/09n.png
datapanels/images/10d.png
datapanels/images/10n.png
datapanels/images/11d.png
datapanels/images/11n.png
datapanels/images/13d.png
datapanels/images/13n.png
datapanels/images/50d.png
datapanels/images/50n.png
datapanels/images/__init__.py
datapanels-0.1.3.dist-info/LICENSE
datapanels-0.1.3.dist-info/METADATA
datapanels-0.1.3.dist-info/WHEEL
datapanels-0.1.3.dist-info/top_level.txt
datapanels-0.1.3.dist-info/RECORD
