Metadata-Version: 2.1
Name: datapanels
Version: 0.1.3
Summary: An application for displaying a rotating set of information panels
Home-page: https://github.com/man-vs-electron/datapanels
Author: Man vs Electron
Author-email: manvselectron@gmail.com
License: Apache Software License
Project-URL: Bug Tracker, https://github.com/man-vs-electron/datapanels/issues
Platform: UNKNOWN
Classifier: Development Status :: 4 - Beta
Classifier: Topic :: Software Development :: User Interfaces
Classifier: License :: OSI Approved :: Apache Software License
Requires-Python: >=3.6
License-File: LICENSE
Requires-Dist: kivy (==2.0.0)
Requires-Dist: kwidgets (>=0.1.2)
Requires-Dist: kivy-garden.graph
Requires-Dist: yfinance
Requires-Dist: pyowm
